{"33": {"bleed_through": {"mean": 0.0187, "sd": 0.0165}, "snr_sd": 0.001075}, "46": {"bleed_through": {"mean": 0.0164, "sd": 0.0105}, "snr_sd": 0.001075}, "34": {"bleed_through": {"mean": 0.0111, "sd": 0.0025}, "snr_sd": 0.0015275}, "146": {"bleed_through": {"mean": 0.1372, "sd": 0.0537}, "snr_sd": 0.00097}, "54": {"bleed_through": {"mean": 0.0092, "sd": 0.0055}, "snr_sd": 0.001385}, "53": {"bleed_through": {"mean": 0.0134, "sd": 0.0079}, "snr_sd": 0.00138}, "32": [{"start_date": "2016-01-01", "end_date": "2016-07-12", "snr_sd": 0.000505, "bleed_through": {"mean": 0.017, "sd": 0.0072}}, {"start_date": "2016-07-13", "end_date": "2017-11-21", "snr_sd": 0.001223, "bleed_through": {"mean": 0.017, "sd": 0.0072}}, {"start_date": "2017-11-22", "end_date": "2019-12-31", "snr_sd": 0.002229, "bleed_through": {"mean": 0.0121, "sd": 0.0071}}]}